{"CORMVH_MODFOR":"CO","CORMVI_NROITM":2,"CORMVI_TIPPRO":"SSF   ","CORMVI_ARTCOD":"07-022-023","CORMVI_PRECIO":5567.76,"CORMVI_CANTID":224,"CORMVI_UNIMED":"U","CORMVI_NROORI":[4544,4544],"CORMVI_COFLIS":"ARS","CORMVI_PRENAC":5567.76,"CORMVI_TOTLIN":1247178.24,"USR_CORMVI_FECHDESENT":"2026-05-18T00:00:00.000Z","USR_CORMVI_PCOTIZ":5567.76,"CORMVH_CODFOR":"OCL","CORMVH_NROFOR":5544,"CORMVH_FCHMOV":"2026-05-19T00:00:00.000Z","CORMVH_NROCTA":"200027","CORMVH_COFLIS":"ARS","CORMVH_COFFAC":"ARS","CORMVH_COFDEU":"ARS","NROCTA":"PRET SANTE S.A. (ENLOZADORA)","DESCRIPCION":"SDH - CONDUCTO Ø 6\" ENLOZADO","PREUNI":5567.76,"":[1247178.24,"2026-05-18T00:00:00.000Z"],"USDDIA":1,"TOTALREAL":1247178.24}